{
  "apothem": {
    "repo": "beny-plugin-repo-beta-1001",
    "address": "0x74Fc8C0d04658940279c5F4f5F4758b9067f7e2E",
    "args": [],
    "blockNumberOfDeployment": 58359945,
    "releases": {
      "1": {
        "builds": {
          "1": {
            "setup": {
              "name": "DaofinPluginSetup",
              "address": "0x62Dc248F0499F6e6A8985a284326DD250d4c99C0",
              "args": [],
              "blockNumberOfDeployment": 58359947
            },
            "implementation": {
              "name": "DaofinPlugin",
              "address": "0xbe8450a977B1d17bf518117E1B13C5E3143634a6",
              "args": [],
              "blockNumberOfDeployment": 58359947
            },
            "helpers": [],
            "buildMetadataURI": "ipfs://QmV3XAX9eniRBeipi2n4dA6EqT4JaUSaTE5ftnVnoYApiv",
            "blockNumberOfPublication": 58359950
          }
        },
        "releaseMetadataURI": "ipfs://QmbJWAESqCsf4RFCqEY7jecCashj8usXiyDNfKtZCwwzGb"
      }
    }
  },
  "anvil": {
    "repo": "beny-plugin-repo-1003",
    "address": "0x75A6BC1bD4A578864F9b45A7935245D22F8d393A",
    "args": [],
    "blockNumberOfDeployment": 54098625,
    "releases": {
      "1": {
        "builds": {
          "1": {
            "setup": {
              "name": "DaofinPluginSetup",
              "address": "0x4C2F7092C2aE51D986bEFEe378e50BD4dB99C901",
              "args": [],
              "blockNumberOfDeployment": 54098626
            },
            "implementation": {
              "name": "DaofinPlugin",
              "address": "0x1ddA04de7bAff86E7Ab325E203EA68BCf9D2D9eA",
              "args": [],
              "blockNumberOfDeployment": 54098626
            },
            "helpers": [],
            "buildMetadataURI": "ipfs://QmYkd6CnaDpeeHg2YnaHCFFRtdvBYw1p3R25skJKCgqZot",
            "blockNumberOfPublication": 54098627
          }
        },
        "releaseMetadataURI": "ipfs://QmbJWAESqCsf4RFCqEY7jecCashj8usXiyDNfKtZCwwzGb"
      }
    }
  }
}
